bitmap.cpython-310-i386-linux-gnu.so
cbitmap/cbitmap.py
cbitmap/__init__.py
cbitmap-0.0.5.dist-info/METADATA
cbitmap-0.0.5.dist-info/top_level.txt
cbitmap-0.0.5.dist-info/WHEEL
cbitmap-0.0.5.dist-info/RECORD
