Metadata-Version: 2.1
Name: cbitmap
Version: 0.0.5
Summary: A C-based bitmap implementation.
Home-page: https://github.com/dwpeng/bitmap
Author: dwpeng
Author-email: 1732889554@qq.com
License: UNKNOWN
Platform: UNKNOWN
Requires-Python: >=3.6
